datafilter/__init__.py
datafilter/base.py
datafilter/config.py
datafilter/filters.py
datafilter/mixins.py
datafilter-0.4.2.dist-info/LICENSE.md
datafilter-0.4.2.dist-info/METADATA
datafilter-0.4.2.dist-info/WHEEL
datafilter-0.4.2.dist-info/top_level.txt
datafilter-0.4.2.dist-info/RECORD
