Metadata-Version: 2.1
Name: datafilter
Version: 0.4.2
Summary: Quickly find tokens (words, phrases, etc) within your data.
Home-page: https://github.com/jcp/datafilter
Author: James C. Palmer
Author-email: me@jcp.io
License: BSD 3-Clause
Platform: UNKNOWN
Classifier: Development Status :: 5 - Production/Stable
Classifier: Intended Audience :: Developers
Classifier: License :: OSI Approved :: BSD License
Classifier: Operating System :: OS Independent
Classifier: Programming Language :: Python
Classifier: Programming Language :: Python :: 3
Classifier: Programming Language :: Python :: 3.6
Classifier: Programming Language :: Python :: 3.7
Requires-Python: >=3.6
